UConnRCMPy-3.0.5.dist-info/DESCRIPTION.rst
UConnRCMPy-3.0.5.dist-info/LICENSE.txt
UConnRCMPy-3.0.5.dist-info/METADATA
UConnRCMPy-3.0.5.dist-info/RECORD
UConnRCMPy-3.0.5.dist-info/WHEEL
UConnRCMPy-3.0.5.dist-info/entry_points.txt
UConnRCMPy-3.0.5.dist-info/metadata.json
UConnRCMPy-3.0.5.dist-info/top_level.txt
uconnrcmpy/__init__.py
uconnrcmpy/_version.py
uconnrcmpy/conditions.py
uconnrcmpy/constants.py
uconnrcmpy/experiments.py
uconnrcmpy/simulations.py
uconnrcmpy/traces.py
uconnrcmpy/tests/00_in_00_mm_333K-1146t-100x-21-Jul-15-1226.txt
uconnrcmpy/tests/NR_00_in_00_mm_333K-1137t-100x-21-Jul-15-1251.txt
uconnrcmpy/tests/__init__.py
uconnrcmpy/tests/species.cti
uconnrcmpy/tests/test_conditions.py
uconnrcmpy/tests/test_constants.py
uconnrcmpy/tests/test_experiments.py
