Metadata-Version: 2.0
Name: UConnRCMPy
Version: 3.0.5
Summary: A package to process RCM data
Home-page: https://github.com/bryanwweber/UConnRCMPy
Author: Bryan W. Weber
Author-email: bryan.weber@uconn.edu
License: MIT
Platform: UNKNOWN
Classifier: Development Status :: 4 - Beta
Classifier: License :: OSI Approved :: BSD License
Classifier: Programming Language :: Python :: 3
Classifier: Programming Language :: Python :: 3.4
Classifier: Programming Language :: Python :: 3.5
Classifier: Programming Language :: Python :: 3.6
Requires-Dist: cantera (>=2.3.0)
Requires-Dist: matplotlib (>=1.4.0)
Requires-Dist: numpy (>=1.8.0)
Requires-Dist: pyperclip (>=1.5.27)
Requires-Dist: pyyaml (>-3.12)
Requires-Dist: scipy (>=0.18.0)
